acquisition_case_transform/__init__.py
acquisition_case_transform/__main__.py
acquisition_case_transform/bad_gr.py
acquisition_case_transform/bad_l.py
acquisition_case_transform/bad_offg.py
acquisition_case_transform/bad_phil.py
acquisition_case_transform/bad_prom_date.py
acquisition_case_transform/bad_scra.py
acquisition_case_transform/bad_space_date.py
acquisition_case_transform-0.1.2.dist-info/WHEEL
acquisition_case_transform-0.1.2.dist-info/METADATA
acquisition_case_transform-0.1.2.dist-info/RECORD
