Metadata-Version: 2.1
Name: acquisition-case-transform
Version: 0.1.2
Summary: Fix typograpic errors / non-standard Supreme Court citations
Author: Marcelino G. Veloso III
Author-email: mars@veloso.one
Requires-Python: >=3.10,<4.0
Classifier: Programming Language :: Python :: 3
Classifier: Programming Language :: Python :: 3.10
Requires-Dist: citation-date (>=0.0.2,<0.0.3)
